setup.cfg
setup.py
yts/__init__.py
yts/rawyify.py
yts.egg-info/PKG-INFO
yts.egg-info/SOURCES.txt
yts.egg-info/dependency_links.txt
yts.egg-info/not-zip-safe
yts.egg-info/requires.txt
yts.egg-info/top_level.txt