Metadata-Version: 1.1
Name: yts
Version: 0.3
Summary: a python powered movie torrent downloader
Home-page: http://github.com/storborg/funniest
Author: NarenArya
Author-email: narenarya@live.com
License: MIT
Platform: UNKNOWN
Classifier: Programming Language :: Python
Classifier: Programming Language :: Python :: 2.7
Classifier: License :: OSI Approved :: BSD License
Classifier: Operating System :: POSIX :: Linux
